[
  {
    "def_cn": "<span class=\"text_blue\">存在的;现存的</span>",
    "def_en": "<span class=\"endef\"><span class=\"st\" onmouseout=\"st_mouseout(this)\" onmouseover=\"st_mouseover(this)\" style=\"font-weight:bold;\">See also:</span><b class=\"text_blue\"><a class=\"explain\" href=\"entry://non-existent\">non-existent</a></b>;\r You can describe something as <b>existent</b> when it exists.  \r \r\r\r</span>",
    "display_hwd": "existent",
    "ext": "",
    "hwd": "existent",
    "phonetics": "英\r[ɪgˈzɪstənt]美\r[ɪɡˈzɪstənt]",
    "phrase": "",
    "sense": "adj\t\t\t\t\t\t\t\t\t\t\t"
  }
]