[
  {
    "def_cn": "<span class=\"text_blue\">过分强调；过分注重</span>",
    "def_en": "<span class=\"endef\">\r\r\r If you say that someone <b>overemphasizes</b> something, you mean that they give it more importance than it deserves or than you consider appropriate.  \r \r\r\r</span>",
    "display_hwd": "overemphasize",
    "ext": "",
    "hwd": "overemphasize",
    "phonetics": "英\r[ˌəʊvər'emfəsaɪz]美\r[ˌovɚˈɛmfəˌsaɪz]",
    "phrase": "",
    "sense": "verb\t\t\t\t\t\t\t\t\t\t\t"
  },
  {
    "def_cn": "<span class=\"text_blue\">再怎么强调（都不为过）</span>",
    "def_en": "<span class=\"endef\">\r\r\r If you say that something <b>cannot be overemphasized</b>, you are emphasizing that you think it is very important.  \r \r\r\r</span>",
    "display_hwd": "overemphasize",
    "ext": "",
    "hwd": "overemphasize",
    "phonetics": "英\r[ˌəʊvər'emfəsaɪz]美\r[ˌovɚˈɛmfəˌsaɪz]",
    "phrase": "",
    "sense": "verb\t\t\t\t\t\t\t\t\t\t\t"
  }
]