[
  {
    "def_cn": "<span class=\"text_blue\">（统称）使馆官员;大使馆</span>",
    "def_en": "<span class=\"endef\">\r\r\r An <b>embassy</b> is a group of government officials, headed by an ambassador, who represent their government in a foreign country. The building in which they work is also called an <b>embassy</b> .  \r \r\r\r</span>",
    "display_hwd": "embassy",
    "ext": "",
    "hwd": "embassy",
    "phonetics": "英\r[ˈembəsi]美\r[ˈɛmbəsi]",
    "phrase": "",
    "sense": "★★★☆☆ n-count\t\t\t\t\t\t\t\t\t\t\t"
  }
]