[
  {
    "def_cn": "<span class=\"text_blue\">赋予;使天生拥有</span>",
    "def_en": "<span class=\"endef\">\r\r\r You say that someone <b>is endowed with</b> a particular desirable ability, characteristic, or possession when they have it by chance or by birth.  \r \r\r\r</span>",
    "display_hwd": "endow",
    "ext": "",
    "hwd": "endow",
    "phonetics": "英\r[ɪnˈdaʊ]美\r[ɛnˈdaʊ]",
    "phrase": "",
    "sense": "★☆☆☆☆ verb\t\t\t\t\t\t\t\t\t\t\t"
  },
  {
    "def_cn": "<span class=\"text_blue\">赋予，给予（品质等）</span>",
    "def_en": "<span class=\"endef\">\r\r\r If you <b>endow</b> something <b>with</b> a particular feature or quality, you provide it with that feature or quality.  \r \r\r\r</span>",
    "display_hwd": "endow",
    "ext": "",
    "hwd": "endow",
    "phonetics": "英\r[ɪnˈdaʊ]美\r[ɛnˈdaʊ]",
    "phrase": "",
    "sense": "★☆☆☆☆ verb\t\t\t\t\t\t\t\t\t\t\t"
  },
  {
    "def_cn": "<span class=\"text_blue\">资助，捐助(机构、奖学金、项目等)</span>",
    "def_en": "<span class=\"endef\">\r\r\r If someone <b>endows</b> an institution, scholarship, or project, they provide a large amount of money which will produce the income needed to pay for it.  \r \r\r\r</span>",
    "display_hwd": "endow",
    "ext": "",
    "hwd": "endow",
    "phonetics": "英\r[ɪnˈdaʊ]美\r[ɛnˈdaʊ]",
    "phrase": "",
    "sense": "★☆☆☆☆ verb\t\t\t\t\t\t\t\t\t\t\t"
  },
  {
    "def_cn": "<span class=\"text_blue\"></span>",
    "def_en": "<span class=\"endef\"><b class=\"text_blue\"><a class=\"explain\" href=\"entry://well-endowed\">well-endowed</a></b>;\r   \r \r\r\r</span>",
    "display_hwd": "endow",
    "ext": "",
    "hwd": "endow",
    "phonetics": "英\r[ɪnˈdaʊ]美\r[ɛnˈdaʊ]",
    "phrase": "",
    "sense": "★☆☆☆☆ see also:"
  }
]