[
  {
    "def_cn": "<span class=\"text_blue\">（清晰地）念（词）；（清晰地）发（音）</span>",
    "def_en": "<span class=\"endef\">\r\r\r When you <b>enunciate</b> a word or part of a word, you pronounce it clearly.  \r \r\r\r</span>",
    "display_hwd": "enunciate",
    "ext": "",
    "hwd": "enunciate",
    "phonetics": "英\r[ɪˈnʌnsieɪt]美\r[ɪˈnʌnsiˌet]",
    "phrase": "",
    "sense": "verb\t\t\t\t\t\t\t\t\t\t\t"
  },
  {
    "def_cn": "<span class=\"text_blue\">阐明；清楚而准确地阐释</span>",
    "def_en": "<span class=\"endef\">\r\r\r When you <b>enunciate</b> a thought, idea, or plan, you express it very clearly and precisely.  \r \r\r\r</span>",
    "display_hwd": "enunciate",
    "ext": "",
    "hwd": "enunciate",
    "phonetics": "英\r[ɪˈnʌnsieɪt]美\r[ɪˈnʌnsiˌet]",
    "phrase": "",
    "sense": "verb\t\t\t\t\t\t\t\t\t\t\t"
  }
]