[
  {
    "def_cn": "<span class=\"text_blue\">夜间;夜晚</span>",
    "def_en": "<span class=\"endef\">\r\r\r The <b>night</b> is the part of each day when the sun has set and it is dark outside, especially the time when people are sleeping.  \r \r\r\r</span>",
    "display_hwd": "night",
    "ext": "",
    "hwd": "night",
    "phonetics": "英\r[naɪt]美\r[naɪt]",
    "phrase": "",
    "sense": "★★★★★ n-var\t\t\t\t\t\t\t\t\t\t\t"
  },
  {
    "def_cn": "<span class=\"text_blue\">晚间，晚上(尤指睡觉前放松的时间)</span>",
    "def_en": "<span class=\"endef\">\r\r\r The <b>night</b> is the period of time between the end of the afternoon and the time that you go to bed, especially the time when you relax before going to bed.  \r \r\r\r</span>",
    "display_hwd": "night",
    "ext": "",
    "hwd": "night",
    "phonetics": "英\r[naɪt]美\r[naɪt]",
    "phrase": "",
    "sense": "★★★★★ n-count\t\t\t\t\t\t\t\t\t\t\t"
  },
  {
    "def_cn": "<span class=\"text_blue\">(演出等的)夜场，夜间活动，…之夜</span>",
    "def_en": "<span class=\"endef\">\r\r\r A particular <b>night</b> is a particular evening when a special event takes place, such as a show or a play.  \r \r\r\r</span>",
    "display_hwd": "night",
    "ext": "",
    "hwd": "night",
    "phonetics": "英\r[naɪt]美\r[naɪt]",
    "phrase": "",
    "sense": "★★★★★ n-count\t\t\t\t\t\t\t\t\t\t\t"
  },
  {
    "def_cn": "<span class=\"text_blue\">晚间;晚上</span>",
    "def_en": "<span class=\"endef\">\r\r\r If it is a particular time <b>at night</b>, it is during the time when it is dark and is before midnight.  \r \r\r\r</span>",
    "display_hwd": "night",
    "ext": "",
    "hwd": "night",
    "phonetics": "英\r[naɪt]美\r[naɪt]",
    "phrase": "",
    "sense": "★★★★★ phrase\t\t\t\t\t\t\t\t\t\t\t"
  },
  {
    "def_cn": "<span class=\"text_blue\">在晚间;在夜里</span>",
    "def_en": "<span class=\"endef\">\r\r\r If something happens <b>at night</b>, it happens regularly during the evening or night.  \r \r\r\r</span>",
    "display_hwd": "night",
    "ext": "",
    "hwd": "night",
    "phonetics": "英\r[naɪt]美\r[naɪt]",
    "phrase": "",
    "sense": "★★★★★ phrase\t\t\t\t\t\t\t\t\t\t\t"
  },
  {
    "def_cn": "<span class=\"text_blue\">昼夜不断;夜以继日</span>",
    "def_en": "<span class=\"endef\">\r\r\r If something happens <b>day and night</b> or <b>night and day</b>, it happens all the time without stopping.  \r \r\r\r</span>",
    "display_hwd": "night",
    "ext": "",
    "hwd": "night",
    "phonetics": "英\r[naɪt]美\r[naɪt]",
    "phrase": "",
    "sense": "★★★★★ phrase\t\t\t\t\t\t\t\t\t\t\t"
  },
  {
    "def_cn": "<span class=\"text_blue\">睡得早/睡得晚</span>",
    "def_en": "<span class=\"endef\">\r\r\r If you have <b>an early night</b>, you go to bed early. If you have <b>a late night</b>, you go to bed late.  \r \r\r\r</span>",
    "display_hwd": "night",
    "ext": "",
    "hwd": "night",
    "phonetics": "英\r[naɪt]美\r[naɪt]",
    "phrase": "",
    "sense": "★★★★★ phrase\t\t\t\t\t\t\t\t\t\t\t"
  },
  {
    "def_cn": "<span class=\"text_blue\"></span>",
    "def_en": "<span class=\"endef\">\r\r   \r<b>morning, noon and night</b><span class=\"text_gray\" style=\"font-weight:bold;\">→see: </span><b class=\"text_blue\"><a class=\"explain\" href=\"entry://morning\">morning</a></b>; \r \r\r\r</span>",
    "display_hwd": "night",
    "ext": "",
    "hwd": "night",
    "phonetics": "英\r[naɪt]美\r[naɪt]",
    "phrase": "",
    "sense": "★★★★★ "
  }
]