[
  {
    "def_cn": "<span class=\"text_blue\">讨厌的;糟透的</span>",
    "def_en": "<span class=\"endef\">\r\r\r If you describe something or someone as <b>horrible</b>, you do not like them at all.  \r \r\r\r</span>",
    "display_hwd": "horribly",
    "ext": "",
    "hwd": "horribly",
    "phonetics": "英\r['hɒrəblɪ]美\r[ˈhɔrəblɪ]",
    "phrase": "",
    "sense": "★★☆☆☆ adj-graded\t\t\t\t\t\t\t\t\t\t\t"
  },
  {
    "def_cn": "<span class=\"text_blue\">令人震惊的;使人恐惧的;让人极度反感的</span>",
    "def_en": "<span class=\"endef\">\r\r\r You can call something <b>horrible</b> when it causes you to feel great shock, fear, and disgust.  \r \r\r\r</span>",
    "display_hwd": "horribly",
    "ext": "",
    "hwd": "horribly",
    "phonetics": "英\r['hɒrəblɪ]美\r[ˈhɔrəblɪ]",
    "phrase": "",
    "sense": "★★☆☆☆ adj-graded\t\t\t\t\t\t\t\t\t\t\t"
  },
  {
    "def_cn": "<span class=\"text_blue\">极严重的</span>",
    "def_en": "<span class=\"endef\"><b>Horrible</b> is used to emphasize how bad something is.  \r \r\r\r</span>",
    "display_hwd": "horribly",
    "ext": "",
    "hwd": "horribly",
    "phonetics": "英\r['hɒrəblɪ]美\r[ˈhɔrəblɪ]",
    "phrase": "",
    "sense": "★★☆☆☆ adj-graded\t\t\t\t\t\t\t\t\t\t\t"
  }
]