[
  {
    "def_cn": "<span class=\"text_blue\">晚宴舞会;(筵席结束后有舞会的)正式宴会</span>",
    "def_en": "<span class=\"endef\">\r\r\r A <b>dinner dance</b> is a social event where a large number of people come to have dinner and to dance. Dinner dances are held in the evening at hotels, restaurants, and social clubs.  \r \r\r\r</span>",
    "display_hwd": "dinner dance",
    "ext": "",
    "hwd": "dinner dance",
    "phonetics": "英\r[ˈdinədɑ:ns]美\r[ˈdɪnɚdæns]",
    "phrase": "",
    "sense": "n-count\t\t\t\t\t\t\t\t\t\t\t"
  }
]