[
  {
    "def_cn": "<span class=\"text_blue\">打扰;干扰;妨碍</span>",
    "def_en": "<span class=\"endef\">\r\r\r If you <b>disturb</b> someone, you interrupt what they are doing and upset them.  \r \r\r\r</span>",
    "display_hwd": "disturb",
    "ext": "",
    "hwd": "disturb",
    "phonetics": "英\r[dɪˈstɜ:b]美\r[dɪˈstɜrb]",
    "phrase": "",
    "sense": "★★☆☆☆ verb\t\t\t\t\t\t\t\t\t\t\t"
  },
  {
    "def_cn": "<span class=\"text_blue\">使焦虑;使不安;使烦恼</span>",
    "def_en": "<span class=\"endef\">\r\r\r If something <b>disturbs</b> you, it makes you feel upset or worried.  \r \r\r\r</span>",
    "display_hwd": "disturb",
    "ext": "",
    "hwd": "disturb",
    "phonetics": "英\r[dɪˈstɜ:b]美\r[dɪˈstɜrb]",
    "phrase": "",
    "sense": "★★☆☆☆ verb\t\t\t\t\t\t\t\t\t\t\t"
  },
  {
    "def_cn": "<span class=\"text_blue\">搅乱;弄乱;搞乱</span>",
    "def_en": "<span class=\"endef\">\r\r\r If something <b>is disturbed</b>, its position or shape is changed.  \r \r\r\r</span>",
    "display_hwd": "disturb",
    "ext": "",
    "hwd": "disturb",
    "phonetics": "英\r[dɪˈstɜ:b]美\r[dɪˈstɜrb]",
    "phrase": "",
    "sense": "★★☆☆☆ verb\t\t\t\t\t\t\t\t\t\t\t"
  },
  {
    "def_cn": "<span class=\"text_blue\">干扰，破坏(形势、氛围)</span>",
    "def_en": "<span class=\"endef\">\r\r\r If something <b>disturbs</b> a situation or atmosphere, it spoils it or causes trouble.  \r \r\r\r</span>",
    "display_hwd": "disturb",
    "ext": "",
    "hwd": "disturb",
    "phonetics": "英\r[dɪˈstɜ:b]美\r[dɪˈstɜrb]",
    "phrase": "",
    "sense": "★★☆☆☆ verb\t\t\t\t\t\t\t\t\t\t\t"
  },
  {
    "def_cn": "<span class=\"text_blue\">扰乱治安</span>",
    "def_en": "<span class=\"endef\">\r\r\r If someone is accused of <b>disturbing the peace</b>, they are accused of behaving in a noisy and offensive way in public.  \r \r\r\r</span>",
    "display_hwd": "disturb",
    "ext": "",
    "hwd": "disturb",
    "phonetics": "英\r[dɪˈstɜ:b]美\r[dɪˈstɜrb]",
    "phrase": "",
    "sense": "★★☆☆☆ phrase\t\t\t\t\t\t\t\t\t\t\t"
  }
]