[
  {
    "def_cn": "<span class=\"text_blue\">细微差别;微妙之处</span>",
    "def_en": "<span class=\"endef\"><b>Subtleties</b> are very small details or differences which are not obvious.  \r \r\r\r</span>",
    "display_hwd": "subtlety",
    "ext": "",
    "hwd": "subtlety",
    "phonetics": "英\r[ˈsʌtlti]美\r[ˈsʌtlti]",
    "phrase": "",
    "sense": "★☆☆☆☆ n-count\t\t\t\t\t\t\t\t\t\t\t"
  },
  {
    "def_cn": "<span class=\"text_blue\">精妙;精细;细微;微妙</span>",
    "def_en": "<span class=\"endef\"><b>Subtlety</b> is the quality of being not immediately obvious or noticeable, and therefore difficult to describe.  \r \r\r\r</span>",
    "display_hwd": "subtlety",
    "ext": "",
    "hwd": "subtlety",
    "phonetics": "英\r[ˈsʌtlti]美\r[ˈsʌtlti]",
    "phrase": "",
    "sense": "★☆☆☆☆ n-uncount\t\t\t\t\t\t\t\t\t\t\t"
  },
  {
    "def_cn": "<span class=\"text_blue\">细致;敏锐</span>",
    "def_en": "<span class=\"endef\"><b>Subtlety</b> is the ability to notice and recognize things which are not obvious, especially small differences between things.  \r \r\r\r</span>",
    "display_hwd": "subtlety",
    "ext": "",
    "hwd": "subtlety",
    "phonetics": "英\r[ˈsʌtlti]美\r[ˈsʌtlti]",
    "phrase": "",
    "sense": "★☆☆☆☆ n-uncount\t\t\t\t\t\t\t\t\t\t\t"
  },
  {
    "def_cn": "<span class=\"text_blue\">诡秘;狡猾;巧妙</span>",
    "def_en": "<span class=\"endef\"><b>Subtlety</b> is the ability to use indirect methods to achieve something, rather than doing something that is obvious.  \r \r\r\r</span>",
    "display_hwd": "subtlety",
    "ext": "",
    "hwd": "subtlety",
    "phonetics": "英\r[ˈsʌtlti]美\r[ˈsʌtlti]",
    "phrase": "",
    "sense": "★☆☆☆☆ n-uncount\t\t\t\t\t\t\t\t\t\t\t"
  }
]