[
  {
    "def_cn": "<span class=\"text_blue\">愚蠢的;幼稚的;荒唐的</span>",
    "def_en": "<span class=\"endef\">\r\r\r If you say that someone or something is <b>silly</b>, you mean that they are foolish, childish, or ridiculous.  \r \r\r\r</span>",
    "display_hwd": "silly",
    "ext": "",
    "hwd": "silly",
    "phonetics": "英\r[ˈsɪli]美\r[ˈsɪli]",
    "phrase": "",
    "sense": "★★☆☆☆ adj-graded\t\t\t\t\t\t\t\t\t\t\t"
  },
  {
    "def_cn": "<span class=\"text_blue\">(喝得)昏头昏脑的;(笑得)傻里傻气的</span>",
    "def_en": "<span class=\"endef\">\r\r\r If you do something such as laugh or drink <b>yourself silly</b>, you do it so much that you are unable to think or behave sensibly.  \r \r\r\r</span>",
    "display_hwd": "silly",
    "ext": "",
    "hwd": "silly",
    "phonetics": "英\r[ˈsɪli]美\r[ˈsɪli]",
    "phrase": "",
    "sense": "★★☆☆☆ adj\t\t\t\t\t\t\t\t\t\t\t"
  }
]