[
  {
    "def_cn": "<span class=\"text_blue\">哀号;悲鸣;恸哭</span>",
    "def_en": "<span class=\"endef\">\r\r\r If someone <b>wails</b>, they make long, loud, high-pitched cries which express sorrow or pain.  \r \r\r\r</span>",
    "display_hwd": "wailing",
    "ext": "",
    "hwd": "wailing",
    "phonetics": "[weilɪŋ]",
    "phrase": "",
    "sense": "★☆☆☆☆ verb\t\t\t\t\t\t\t\t\t\t\t"
  },
  {
    "def_cn": "<span class=\"text_blue\">哀诉;哀号着说</span>",
    "def_en": "<span class=\"endef\">\r\r\r If you <b>wail</b> something, you say it in a loud, high-pitched voice that shows that you are unhappy or in pain.  \r \r\r\r</span>",
    "display_hwd": "wailing",
    "ext": "",
    "hwd": "wailing",
    "phonetics": "[weilɪŋ]",
    "phrase": "",
    "sense": "★☆☆☆☆ verb\t\t\t\t\t\t\t\t\t\t\t"
  },
  {
    "def_cn": "<span class=\"text_blue\">(警报器等)尖叫，尖啸</span>",
    "def_en": "<span class=\"endef\">\r\r\r If something such as a siren or an alarm <b>wails</b>, it makes a long, loud, high-pitched sound.  \r \r\r\r</span>",
    "display_hwd": "wailing",
    "ext": "",
    "hwd": "wailing",
    "phonetics": "[weilɪŋ]",
    "phrase": "",
    "sense": "★☆☆☆☆ verb\t\t\t\t\t\t\t\t\t\t\t"
  }
]