[
  {
    "def_cn": "<span class=\"text_blue\">（通常指盗贼）闯入，破门而入</span>",
    "def_en": "<span class=\"endef\"><span class=\"st\" onmouseout=\"st_mouseout(this)\" onmouseover=\"st_mouseover(this)\" style=\"font-weight:bold;\">See also:</span><b class=\"text_blue\"><a class=\"explain\" href=\"entry://break-in\">break-in</a></b>;\r If someone, usually a thief, <b>breaks in</b>, they get into a building by force.  \r \r\r\r</span>",
    "display_hwd": "break in",
    "ext": "",
    "hwd": "break in",
    "phonetics": "英\r[breikin]美\r[brekɪn]",
    "phrase": "",
    "sense": "phrasal verb\t\t\t\t\t\t\t\t\t\t\t"
  },
  {
    "def_cn": "<span class=\"text_blue\">打断；插嘴</span>",
    "def_en": "<span class=\"endef\">\r\r\r If you <b>break in</b> on someone's conversation or activity, you interrupt them.  \r \r\r\r</span>",
    "display_hwd": "break in",
    "ext": "",
    "hwd": "break in",
    "phonetics": "英\r[breikin]美\r[brekɪn]",
    "phrase": "",
    "sense": "phrasal verb\t\t\t\t\t\t\t\t\t\t\t"
  },
  {
    "def_cn": "<span class=\"text_blue\">使适应（新的工作或环境）</span>",
    "def_en": "<span class=\"endef\">\r\r\r If you <b>break</b> someone <b>in</b>, you get them used to a new job or situation.  \r \r\r\r</span>",
    "display_hwd": "break in",
    "ext": "",
    "hwd": "break in",
    "phonetics": "英\r[breikin]美\r[brekɪn]",
    "phrase": "",
    "sense": "phrasal verb\t\t\t\t\t\t\t\t\t\t\t"
  },
  {
    "def_cn": "<span class=\"text_blue\">使(新产品）经使用逐渐合用；磨合</span>",
    "def_en": "<span class=\"endef\">\r\r\r If you <b>break in</b> something new, you gradually use or wear it for longer and longer periods until it is ready to be used or worn all the time.  \r \r\r\r</span>",
    "display_hwd": "break in",
    "ext": "",
    "hwd": "break in",
    "phonetics": "英\r[breikin]美\r[brekɪn]",
    "phrase": "",
    "sense": "phrasal verb\t\t\t\t\t\t\t\t\t\t\t"
  }
]