[
  {
    "def_cn": "<span class=\"text_blue\">在…中占首要地位，在…中最具影响力</span>",
    "def_en": "<span class=\"endef\">\r\r\r To <b>dominate</b> a situation means to be the most powerful or important person or thing in it.  \r \r\r\r</span>",
    "display_hwd": "dominate",
    "ext": "",
    "hwd": "dominate",
    "phonetics": "英\r[ˈdɒmɪneɪt]美\r[ˈdɑmɪneɪt]",
    "phrase": "",
    "sense": "★★★★☆ verb\t\t\t\t\t\t\t\t\t\t\t"
  },
  {
    "def_cn": "<span class=\"text_blue\">控制;统治;支配</span>",
    "def_en": "<span class=\"endef\">\r\r\r If one country or person <b>dominates</b> another, they have power over them.  \r \r\r\r</span>",
    "display_hwd": "dominate",
    "ext": "",
    "hwd": "dominate",
    "phonetics": "英\r[ˈdɒmɪneɪt]美\r[ˈdɑmɪneɪt]",
    "phrase": "",
    "sense": "★★★★☆ verb\t\t\t\t\t\t\t\t\t\t\t"
  },
  {
    "def_cn": "<span class=\"text_blue\">俯视;高耸于</span>",
    "def_en": "<span class=\"endef\">\r\r\r If a building, mountain, or other object <b>dominates</b> an area, it is so large or impressive that you cannot avoid seeing it.  \r \r\r\r</span>",
    "display_hwd": "dominate",
    "ext": "",
    "hwd": "dominate",
    "phonetics": "英\r[ˈdɒmɪneɪt]美\r[ˈdɑmɪneɪt]",
    "phrase": "",
    "sense": "★★★★☆ verb\t\t\t\t\t\t\t\t\t\t\t"
  }
]