[
  {
    "def_cn": "<span class=\"text_blue\">（书写）连笔的</span>",
    "def_en": "<span class=\"endef\">\r\r\r In <b>joined-up</b> writing, you join all the letters in each word together, without taking your pen off the paper. This sort of writing is used by older children and adults.  \r \r\r\r</span>",
    "display_hwd": "joined-up",
    "ext": "",
    "hwd": "joined-up",
    "phonetics": "",
    "phrase": "",
    "sense": "adj\t\t\t\t\t\t\t\t\t\t\t"
  },
  {
    "def_cn": "<span class=\"text_blue\">（计划、想法或组织）明智的，精明的，趋于成熟的</span>",
    "def_en": "<span class=\"endef\">\r\r\r Journalists sometimes use <b>joined-up</b> to describe plans, ideas, or organizations which seem sensible, sophisticated, and mature, especially when they think that they have been unsophisticated or immature in the past.  \r \r\r\r</span>",
    "display_hwd": "joined-up",
    "ext": "",
    "hwd": "joined-up",
    "phonetics": "",
    "phrase": "",
    "sense": "adj\t\t\t\t\t\t\t\t\t\t\t"
  }
]