[
  {
    "def_cn": "<span class=\"text_blue\">假装；伪装；装作</span>",
    "def_en": "<span class=\"endef\">\r\r\r If you <b>pretend that</b> something is the case, you act in a way that is intended to make people believe that it is the case, although in fact it is not.  \r \r\r\r</span>",
    "display_hwd": "pretend",
    "ext": "",
    "hwd": "pretend",
    "phonetics": "英\r[prɪˈtend]美\r[prɪˈtɛnd]",
    "phrase": "",
    "sense": "★★☆☆☆ verb\t\t\t\t\t\t\t\t\t\t\t"
  },
  {
    "def_cn": "<span class=\"text_blue\">（做游戏等时）假装，假扮，装扮</span>",
    "def_en": "<span class=\"endef\">\r\r\r If children or adults <b>pretend that</b> they are doing something, they imagine that they are doing it, for example as part of a game.  \r \r\r\r</span>",
    "display_hwd": "pretend",
    "ext": "",
    "hwd": "pretend",
    "phonetics": "英\r[prɪˈtend]美\r[prɪˈtɛnd]",
    "phrase": "",
    "sense": "★★☆☆☆ verb\t\t\t\t\t\t\t\t\t\t\t"
  },
  {
    "def_cn": "<span class=\"text_blue\">自诩；自称；自以为</span>",
    "def_en": "<span class=\"endef\">\r\r\r If you do not <b>pretend that</b> something is the case, you do not claim that it is the case.  \r \r\r\r</span>",
    "display_hwd": "pretend",
    "ext": "",
    "hwd": "pretend",
    "phonetics": "英\r[prɪˈtend]美\r[prɪˈtɛnd]",
    "phrase": "",
    "sense": "★★☆☆☆ verb\t\t\t\t\t\t\t\t\t\t\t"
  }
]