[
  {
    "def_cn": "<span class=\"text_blue\">极拘谨的；一本正经的；古板的</span>",
    "def_en": "<span class=\"endef\">\r\r\r If you describe someone as <b>prim</b>, you disapprove of them because they behave too correctly and are too easily shocked by anything rude.  \r \r\r\r</span>",
    "display_hwd": "primly",
    "ext": "",
    "hwd": "primly",
    "phonetics": "英\r[prɪmlɪ]美\r[prɪmlɪ]",
    "phrase": "",
    "sense": "adj-graded\t\t\t\t\t\t\t\t\t\t\t"
  },
  {
    "def_cn": "<span class=\"text_blue\">整洁的；得体的</span>",
    "def_en": "<span class=\"endef\">\r\r\r If you describe something as <b>prim</b>, you mean that it is very neat, tidy, or sensible.  \r \r\r\r</span>",
    "display_hwd": "primly",
    "ext": "",
    "hwd": "primly",
    "phonetics": "英\r[prɪmlɪ]美\r[prɪmlɪ]",
    "phrase": "",
    "sense": "adj-graded\t\t\t\t\t\t\t\t\t\t\t"
  }
]