[
  {
    "def_cn": "<span class=\"text_blue\">代词；代名词</span>",
    "def_en": "<span class=\"endef\"><span class=\"st\" onmouseout=\"st_mouseout(this)\" onmouseover=\"st_mouseover(this)\" style=\"font-weight:bold;\">See also:</span><b class=\"text_blue\"><a class=\"explain\" href=\"entry://indefinite pronoun\">indefinite pronoun</a></b>;\r<b class=\"text_blue\"><a class=\"explain\" href=\"entry://personal pronoun\">personal pronoun</a></b>;\r<b class=\"text_blue\"><a class=\"explain\" href=\"entry://reflexive pronoun\">reflexive pronoun</a></b>;\r<b class=\"text_blue\"><a class=\"explain\" href=\"entry://relative pronoun\">relative pronoun</a></b>;\r A <b>pronoun</b> is a word that you use to refer to someone or something when you do not need to use a noun, often because the person or thing has been mentioned earlier. Examples are 'it', 'she', 'something', and 'myself'.  \r \r\r\r</span>",
    "display_hwd": "pronoun",
    "ext": "",
    "hwd": "pronoun",
    "phonetics": "英\r[ˈprəʊnaʊn]美\r[ˈproʊnaʊn]",
    "phrase": "",
    "sense": "n-count\t\t\t\t\t\t\t\t\t\t\t"
  }
]