[
  {
    "def_cn": "<span class=\"text_blue\">伸出;探出</span>",
    "def_en": "<span class=\"endef\">\r\r\r If you <b>stick out</b> part of your body, you extend it away from your body.  \rto <b>stick</b> your <b>neck out</b><span class=\"text_gray\" style=\"font-weight:bold;\">→see: </span><b class=\"text_blue\"><a class=\"explain\" href=\"entry://neck\">neck</a></b>; \r \r\r\r</span>",
    "display_hwd": "stick out",
    "ext": "",
    "hwd": "stick out",
    "phonetics": "英\r[stikaut]美\r[stɪkaʊt]",
    "phrase": "",
    "sense": "phrasal verb\t\t\t\t\t\t\t\t\t\t\t"
  },
  {
    "def_cn": "<span class=\"text_blue\">显眼;显得突出</span>",
    "def_en": "<span class=\"endef\">\r\r\r If something <b>sticks out</b>, it is very noticeable because it is unusual.  \rto <b>stick out a mile</b><span class=\"text_gray\" style=\"font-weight:bold;\">→see: </span><b class=\"text_blue\"><a class=\"explain\" href=\"entry://mile\">mile</a></b>; \rto stick out like a sore thumb<span class=\"text_gray\" style=\"font-weight:bold;\">→see: </span><b class=\"text_blue\"><a class=\"explain\" href=\"entry://thumb\">thumb</a></b>; \r \r\r\r</span>",
    "display_hwd": "stick out",
    "ext": "",
    "hwd": "stick out",
    "phonetics": "英\r[stikaut]美\r[stɪkaʊt]",
    "phrase": "",
    "sense": "phrasal verb\t\t\t\t\t\t\t\t\t\t\t"
  },
  {
    "def_cn": "<span class=\"text_blue\">(在逆境中)坚持到底，忍耐到底</span>",
    "def_en": "<span class=\"endef\">\r\r\r If someone in an unpleasant or difficult situation <b>sticks it out</b>, they do not leave or give up.  \r \r\r\r</span>",
    "display_hwd": "stick out",
    "ext": "",
    "hwd": "stick out",
    "phonetics": "英\r[stikaut]美\r[stɪkaʊt]",
    "phrase": "",
    "sense": "phrase\t\t\t\t\t\t\t\t\t\t\t"
  }
]