[
  {
    "def_cn": "<span class=\"text_blue\">塞内加尔的;塞内加尔人的</span>",
    "def_en": "<span class=\"endef\"><b>Senegalese</b> means belonging or relating to Senegal, or to its people or culture.  \r \r\r\r</span>",
    "display_hwd": "Senegalese",
    "ext": "",
    "hwd": "Senegalese",
    "phonetics": "英\r[ˌsenɪɡə'li:z]美\r[ˌsenɪɡə'liz]",
    "phrase": "",
    "sense": "adj\t\t\t\t\t\t\t\t\t\t\t"
  },
  {
    "def_cn": "<span class=\"text_blue\">塞内加尔人;塞内加尔裔人</span>",
    "def_en": "<span class=\"endef\">\r\r\r A <b>Senegalese</b> is a Senegalese citizen, or a person of Senegalese origin.  \r \r\r\r</span>",
    "display_hwd": "Senegalese",
    "ext": "",
    "hwd": "Senegalese",
    "phonetics": "英\r[ˌsenɪɡə'li:z]美\r[ˌsenɪɡə'liz]",
    "phrase": "",
    "sense": "n-count\t\t\t\t\t\t\t\t\t\t\t"
  }
]