[
  {
    "def_cn": "<span class=\"text_blue\">检疫；隔离</span>",
    "def_en": "<span class=\"endef\">\r\r\r If a person or animal is <b>in quarantine</b>, they are being kept separate from other people or animals for a set period of time, usually because they have or may have a disease.  \r \r\r\r</span>",
    "display_hwd": "quarantine",
    "ext": "",
    "hwd": "quarantine",
    "phonetics": "英\r[ˈkwɒrənti:n]美\r[ˈkwɔrəntin]",
    "phrase": "",
    "sense": "★☆☆☆☆ n-uncount\t\t\t\t\t\t\t\t\t\t\t"
  },
  {
    "def_cn": "<span class=\"text_blue\">对…进行隔离检疫</span>",
    "def_en": "<span class=\"endef\">\r\r\r If people or animals <b>are quarantined</b>, they are stopped from having contact with other people or animals. If a place <b>is quarantined</b>, people and animals are prevented from entering or leaving it.  \r \r\r\r</span>",
    "display_hwd": "quarantine",
    "ext": "",
    "hwd": "quarantine",
    "phonetics": "英\r[ˈkwɒrənti:n]美\r[ˈkwɔrəntin]",
    "phrase": "",
    "sense": "★☆☆☆☆ verb\t\t\t\t\t\t\t\t\t\t\t"
  }
]