[
  {
    "def_cn": "<span class=\"text_blue\">恶心的;想呕吐的</span>",
    "def_en": "<span class=\"endef\">\r\r\r If you feel <b>queasy</b> or if you have a <b>queasy</b> stomach, you feel rather ill, as if you are going to be sick.  \r \r\r\r</span>",
    "display_hwd": "queasiness",
    "ext": "",
    "hwd": "queasiness",
    "phonetics": "英\r['kwi:zɪnəs]美\r['kwizɪnəs]",
    "phrase": "",
    "sense": "adj-graded\t\t\t\t\t\t\t\t\t\t\t"
  },
  {
    "def_cn": "<span class=\"text_blue\">忧虑的；不安的;担心的</span>",
    "def_en": "<span class=\"endef\">\r\r\r If you feel <b>queasy</b> about something, you are a little worried about it.  \r \r\r\r</span>",
    "display_hwd": "queasiness",
    "ext": "",
    "hwd": "queasiness",
    "phonetics": "英\r['kwi:zɪnəs]美\r['kwizɪnəs]",
    "phrase": "",
    "sense": "adj-graded\t\t\t\t\t\t\t\t\t\t\t"
  }
]