[
  {
    "def_cn": "<span class=\"text_blue\">操纵的;控制的;善于摆布（他人）的</span>",
    "def_en": "<span class=\"endef\">\r\r\r If you describe someone as <b>manipulative</b>, you disapprove of them because they skilfully force or persuade people to act in the way that they want.  \r \r\r\r</span>",
    "display_hwd": "manipulative",
    "ext": "",
    "hwd": "manipulative",
    "phonetics": "英\r[məˈnɪpjələtɪv]美\r[məˈnɪpjəleɪtɪv]",
    "phrase": "",
    "sense": "★☆☆☆☆ adj-graded\t\t\t\t\t\t\t\t\t\t\t"
  }
]