[
  {
    "def_cn": "<span class=\"text_blue\">财物;(尤指)衣服</span>",
    "def_en": "<span class=\"endef\">\r\r\r You can refer to someone's possessions, especially their clothes, as their <b>clobber</b> .  \r \r\r\r</span>",
    "display_hwd": "clobber",
    "ext": "",
    "hwd": "clobber",
    "phonetics": "英\r[ˈklɒbə(r)]美\r[ˈklɑbə(r)]",
    "phrase": "",
    "sense": "★☆☆☆☆ n-uncount\t\t\t\t\t\t\t\t\t\t\t"
  },
  {
    "def_cn": "<span class=\"text_blue\">打;揍</span>",
    "def_en": "<span class=\"endef\">\r\r\r If you <b>clobber</b> someone, you hit them.  \r \r\r\r</span>",
    "display_hwd": "clobber",
    "ext": "",
    "hwd": "clobber",
    "phonetics": "英\r[ˈklɒbə(r)]美\r[ˈklɑbə(r)]",
    "phrase": "",
    "sense": "★☆☆☆☆ verb\t\t\t\t\t\t\t\t\t\t\t"
  },
  {
    "def_cn": "<span class=\"text_blue\">使受到严重影响;使遭受沉重打击</span>",
    "def_en": "<span class=\"endef\">\r\r\r If a person or company <b>is clobbered by</b> something, they are very badly affected by it.  \r \r\r\r</span>",
    "display_hwd": "clobber",
    "ext": "",
    "hwd": "clobber",
    "phonetics": "英\r[ˈklɒbə(r)]美\r[ˈklɑbə(r)]",
    "phrase": "",
    "sense": "★☆☆☆☆ verb\t\t\t\t\t\t\t\t\t\t\t"
  }
]