[
  {
    "def_cn": "<span class=\"text_blue\">请求;要求</span>",
    "def_en": "<span class=\"endef\">\r\r\r If you <b>request</b> something, you ask for it politely or formally.  \r \r\r\r</span>",
    "display_hwd": "request",
    "ext": "",
    "hwd": "request",
    "phonetics": "英\r[rɪˈkwest]美\r[rɪˈkwɛst]",
    "phrase": "",
    "sense": "★★★★☆ verb\t\t\t\t\t\t\t\t\t\t\t"
  },
  {
    "def_cn": "<span class=\"text_blue\">请求…做;要求…做</span>",
    "def_en": "<span class=\"endef\">\r\r\r If you <b>request</b> someone <b>to</b> do something, you politely or formally ask them to do it.  \r \r\r\r</span>",
    "display_hwd": "request",
    "ext": "",
    "hwd": "request",
    "phonetics": "英\r[rɪˈkwest]美\r[rɪˈkwɛst]",
    "phrase": "",
    "sense": "★★★★☆ verb\t\t\t\t\t\t\t\t\t\t\t"
  },
  {
    "def_cn": "<span class=\"text_blue\">请求;要求</span>",
    "def_en": "<span class=\"endef\">\r\r\r If you make a <b>request</b>, you politely or formally ask someone to do something.  \r \r\r\r</span>",
    "display_hwd": "request",
    "ext": "",
    "hwd": "request",
    "phonetics": "英\r[rɪˈkwest]美\r[rɪˈkwɛst]",
    "phrase": "",
    "sense": "★★★★☆ n-count\t\t\t\t\t\t\t\t\t\t\t"
  },
  {
    "def_cn": "<span class=\"text_blue\">点播的乐曲</span>",
    "def_en": "<span class=\"endef\">\r\r\r A <b>request</b> is a song or piece of music which someone has asked a performer or disc jockey to play.  \r \r\r\r</span>",
    "display_hwd": "request",
    "ext": "",
    "hwd": "request",
    "phonetics": "英\r[rɪˈkwest]美\r[rɪˈkwɛst]",
    "phrase": "",
    "sense": "★★★★☆ n-count\t\t\t\t\t\t\t\t\t\t\t"
  },
  {
    "def_cn": "<span class=\"text_blue\">应邀;应…的请求;按照…的要求</span>",
    "def_en": "<span class=\"endef\">\r\r\r If you do something <b>at</b> someone's <b>request</b>, you do it because they have asked you to.  \r \r\r\r</span>",
    "display_hwd": "request",
    "ext": "",
    "hwd": "request",
    "phonetics": "英\r[rɪˈkwest]美\r[rɪˈkwɛst]",
    "phrase": "",
    "sense": "★★★★☆ phrase\t\t\t\t\t\t\t\t\t\t\t"
  },
  {
    "def_cn": "<span class=\"text_blue\">一经要求;根据请求</span>",
    "def_en": "<span class=\"endef\">\r\r\r If something is given or done <b>on request</b>, it is given or done whenever you ask for it.  \r \r\r\r</span>",
    "display_hwd": "request",
    "ext": "",
    "hwd": "request",
    "phonetics": "英\r[rɪˈkwest]美\r[rɪˈkwɛst]",
    "phrase": "",
    "sense": "★★★★☆ phrase\t\t\t\t\t\t\t\t\t\t\t"
  }
]