[
  {
    "def_cn": "<span class=\"text_blue\">仔细考虑;斟酌</span>",
    "def_en": "<span class=\"endef\"><b>Consideration</b> is careful thought about something.  \r \r\r\r</span>",
    "display_hwd": "consideration",
    "ext": "",
    "hwd": "consideration",
    "phonetics": "英\r[kənˌsɪdəˈreɪʃn]美\r[kənˌsɪdəˈreʃən]",
    "phrase": "",
    "sense": "★★★☆☆ n-uncount\t\t\t\t\t\t\t\t\t\t\t"
  },
  {
    "def_cn": "<span class=\"text_blue\">讨论;考虑</span>",
    "def_en": "<span class=\"endef\">\r\r\r If something is <b>under consideration</b>, it is being discussed.  \r \r\r\r</span>",
    "display_hwd": "consideration",
    "ext": "",
    "hwd": "consideration",
    "phonetics": "英\r[kənˌsɪdəˈreɪʃn]美\r[kənˌsɪdəˈreʃən]",
    "phrase": "",
    "sense": "★★★☆☆ n-uncount\t\t\t\t\t\t\t\t\t\t\t"
  },
  {
    "def_cn": "<span class=\"text_blue\">体贴;体谅;为人着想</span>",
    "def_en": "<span class=\"endef\">\r\r\r If you show <b>consideration</b>, you pay attention to the needs, wishes, or feelings of other people.  \r \r\r\r</span>",
    "display_hwd": "consideration",
    "ext": "",
    "hwd": "consideration",
    "phonetics": "英\r[kənˌsɪdəˈreɪʃn]美\r[kənˌsɪdəˈreʃən]",
    "phrase": "",
    "sense": "★★★☆☆ n-uncount\t\t\t\t\t\t\t\t\t\t\t"
  },
  {
    "def_cn": "<span class=\"text_blue\">(尤指在计划或决定时)应考虑的因素</span>",
    "def_en": "<span class=\"endef\">\r\r\r A <b>consideration</b> is something that should be thought about, especially when you are planning or deciding something.  \r \r\r\r</span>",
    "display_hwd": "consideration",
    "ext": "",
    "hwd": "consideration",
    "phonetics": "英\r[kənˌsɪdəˈreɪʃn]美\r[kənˌsɪdəˈreʃən]",
    "phrase": "",
    "sense": "★★★☆☆ n-count\t\t\t\t\t\t\t\t\t\t\t"
  },
  {
    "def_cn": "<span class=\"text_blue\">考虑到;顾及</span>",
    "def_en": "<span class=\"endef\">\r\r\r If you <b>take</b> something <b>into consideration</b>, you think about it because it is relevant to what you are doing.  \r \r\r\r</span>",
    "display_hwd": "consideration",
    "ext": "",
    "hwd": "consideration",
    "phonetics": "英\r[kənˌsɪdəˈreɪʃn]美\r[kənˌsɪdəˈreʃən]",
    "phrase": "",
    "sense": "★★★☆☆ phrase\t\t\t\t\t\t\t\t\t\t\t"
  }
]