[
  {
    "def_cn": "<span class=\"text_blue\">揭露，发现（隐秘之事）</span>",
    "def_en": "<span class=\"endef\">\r\r\r If you <b>uncover</b> something, especially something that has been kept secret, you discover or find out about it.  \r \r\r\r</span>",
    "display_hwd": "uncover",
    "ext": "",
    "hwd": "uncover",
    "phonetics": "英\r[ʌnˈkʌvə(r)]美\r[ʌnˈkʌvɚ]",
    "phrase": "",
    "sense": "★★☆☆☆ verb\t\t\t\t\t\t\t\t\t\t\t"
  },
  {
    "def_cn": "<span class=\"text_blue\">发现，发掘（地下埋藏之物）</span>",
    "def_en": "<span class=\"endef\">\r\r\r When people who are digging somewhere <b>uncover</b> something, they find a thing or a place that has been under the ground for a long time.  \r \r\r\r</span>",
    "display_hwd": "uncover",
    "ext": "",
    "hwd": "uncover",
    "phonetics": "英\r[ʌnˈkʌvə(r)]美\r[ʌnˈkʌvɚ]",
    "phrase": "",
    "sense": "★★☆☆☆ verb\t\t\t\t\t\t\t\t\t\t\t"
  },
  {
    "def_cn": "<span class=\"text_blue\">揭开…的盖子；除去…上的覆盖物</span>",
    "def_en": "<span class=\"endef\">\r\r\r To <b>uncover</b> something means to remove something that is covering it.  \r \r\r\r</span>",
    "display_hwd": "uncover",
    "ext": "",
    "hwd": "uncover",
    "phonetics": "英\r[ʌnˈkʌvə(r)]美\r[ʌnˈkʌvɚ]",
    "phrase": "",
    "sense": "★★☆☆☆ verb\t\t\t\t\t\t\t\t\t\t\t"
  }
]