[
  {
    "def_cn": "<span class=\"text_blue\">（网球或棒球比赛中负责拾球的）球童，捡球员</span>",
    "def_en": "<span class=\"endef\">\r\r\r In a tennis match, the <b>ball boys</b> pick up any balls that go into the net or off the court and throw them back to the players. In a baseball game, the <b>ball boys</b> are in charge of collecting the balls that are hit out of the field.  \r \r\r\r</span>",
    "display_hwd": "ball boy",
    "ext": "",
    "hwd": "ball boy",
    "phonetics": "英\r[bɔ:lbɔi]美\r[bɔlbɔɪ]",
    "phrase": "",
    "sense": "n-count\t\t\t\t\t\t\t\t\t\t\t"
  }
]